[
  {
    "title": "GDPR Amendment Alert",
    "description": "Proposed GDPR amendment under review in the European Parliament.",
    "timeAgo": "Just now"
  },
  {
    "title": "Surveillance Law Update",
    "description": "France introduces new bill to expand online surveillance powers.",
    "timeAgo": "10 min ago"
  },
  {
    "title": "AI Regulation Framework",
    "description": "Germany supports stricter AI policy on deepfake detection.",
    "timeAgo": "25 min ago"
  },
  {
    "title": "Financial Data Sharing Directive",
    "description": "EU drafts policy mandating open banking data protocols.",
    "timeAgo": "40 min ago"
  }
]